tonl/__init__.py
tonl_py-0.0.1.dist-info/licenses/LICENSE
tonl_py-0.0.1.dist-info/METADATA
tonl_py-0.0.1.dist-info/WHEEL
tonl_py-0.0.1.dist-info/top_level.txt
tonl_py-0.0.1.dist-info/RECORD
