Metadata-Version: 2.4
Name: tonl-py
Version: 0.0.1
Summary: Token-Optimized Notation Language - Python implementation (Placeholder - Full release coming soon)
Author-email: Krypto <mrx.anonymousorg@gmail.com>
License: MIT
Project-URL: Homepage, https://tonl-mcp-bridge-docs.vercel.app
Project-URL: Documentation, https://tonl-mcp-bridge-docs.vercel.app
Project-URL: Repository, https://github.com/kryptomrx/tonl-mcp-bridge
Project-URL: Issues, https://github.com/kryptomrx/tonl-mcp-bridge/issues
Keywords: llm,tokens,compression,json,ai,mcp
Classifier: Development Status :: 1 - Planning
Classifier: Intended Audience :: Developers
Classifier: License :: OSI Approved :: MIT License
Classifier: Programming Language :: Python :: 3
Classifier: Programming Language :: Python :: 3.8
Classifier: Programming Language :: Python :: 3.9
Classifier: Programming Language :: Python :: 3.10
Classifier: Programming Language :: Python :: 3.11
Classifier: Programming Language :: Python :: 3.12
Requires-Python: >=3.8
License-File: LICENSE
Dynamic: license-file
